table_meta/__init__.py
table_meta/core.py
table_meta/ddl_to_meta.py
table_meta/model.py
table_meta/models_to_meta.py
table_meta-0.3.2.dist-info/LICENSE
table_meta-0.3.2.dist-info/WHEEL
table_meta-0.3.2.dist-info/METADATA
table_meta-0.3.2.dist-info/RECORD
