Metadata-Version: 2.1
Name: table-meta
Version: 0.3.2
Summary: Universal class that created to be a middleware, universal mapping for data from different parsers - simple-ddl-parser and py-models-parser
Home-page: https://github.com/xnuinside/table-meta
License: MIT
Author: Iuliia Volkova
Author-email: xnuinside@gmail.com
Requires-Python: >=3.6.2,<4.0
Classifier: License :: OSI Approved :: MIT License
Classifier: Programming Language :: Python :: 3
Classifier: Programming Language :: Python :: 3.7
Classifier: Programming Language :: Python :: 3.8
Classifier: Topic :: Software Development
Classifier: Topic :: Software Development :: Libraries
Classifier: Topic :: Software Development :: Libraries :: Python Modules
Classifier: Topic :: Utilities
Requires-Dist: pydantic (>=1.8.2,<2.0.0)
Project-URL: Repository, https://github.com/xnuinside/table-meta
